{"about_basic_log.md":"15bf53ee","about_basic_todo.md":"281b0666","about_deploy_用github_action自动部署vitepress项目.md":"8e2a9c9f","courses_c高级_note.md":"60e61a39","input_2023-05-27.md":"52283cdd","notes_expr和双括号运算符的区别.md":"dc3b857e","notes_map_originmd_c_adv_day04.md":"d586a5be","notes_map_originmd_c_adv_day03.md":"3cf25a83","output_index.md":"25901cca","notes_map_originmd_index.md":"dd000280","input_2023-05-26.md":"45e1ba0a","index.md":"5e7dda4d","notes_配置vscode remote ssh免密登录.md":"79d080b9","templates_default.md":"65581b01"}
